MANIFEST.in
README.rst
setup.cfg
setup.py
JiveData.egg-info/PKG-INFO
JiveData.egg-info/SOURCES.txt
JiveData.egg-info/dependency_links.txt
JiveData.egg-info/requires.txt
JiveData.egg-info/top_level.txt
jivedata/__init__.py
jivedata/alerts/__init__.py
jivedata/alerts/alerts.py
jivedata/alerts/test/__init__.py
jivedata/alerts/test/test_alerts.py
jivedata/utils/__init__.py
jivedata/utils/clients.py
jivedata/utils/utils.py
jivedata/utils/test/__init__.py
jivedata/utils/test/test_clients.py
jivedata/utils/test/test_utils.py
jivedata/webapp/__init__.py
jivedata/webapp/jinja2_filters.py
jivedata/webapp/static/econ.js
jivedata/webapp/static/filings.js
jivedata/webapp/static/financials.css
jivedata/webapp/static/financials.js
jivedata/webapp/static/insiders.js
jivedata/webapp/static/institutional.js
jivedata/webapp/static/me.css
jivedata/webapp/static/me.js
jivedata/webapp/static/base/main.css
jivedata/webapp/static/base/main.js
jivedata/webapp/static/base/ticker.js
jivedata/webapp/static/images/fav.ico
jivedata/webapp/static/images/loader.gif
jivedata/webapp/static/images/profile_logo_white.png
jivedata/webapp/static/images/startup.png
jivedata/webapp/static/images/touch-icon-ipad-retina.png
jivedata/webapp/static/images/touch-icon-ipad.png
jivedata/webapp/static/images/touch-icon-iphone-retina.png
jivedata/webapp/static/images/jqueryui/animated-overlay.gif
jivedata/webapp/static/images/jqueryui/ui-bg_flat_0_aaaaaa_40x100.png
jivedata/webapp/static/images/jqueryui/ui-bg_flat_75_ffffff_40x100.png
jivedata/webapp/static/images/jqueryui/ui-bg_glass_55_fbf9ee_1x400.png
jivedata/webapp/static/images/jqueryui/ui-bg_glass_65_ffffff_1x400.png
jivedata/webapp/static/images/jqueryui/ui-bg_glass_75_dadada_1x400.png
jivedata/webapp/static/images/jqueryui/ui-bg_glass_75_e6e6e6_1x400.png
jivedata/webapp/static/images/jqueryui/ui-bg_glass_95_fef1ec_1x400.png
jivedata/webapp/static/images/jqueryui/ui-bg_highlight-soft_75_cccccc_1x100.png
jivedata/webapp/static/images/jqueryui/ui-icons_222222_256x240.png
jivedata/webapp/static/images/jqueryui/ui-icons_2e83ff_256x240.png
jivedata/webapp/static/images/jqueryui/ui-icons_454545_256x240.png
