Metadata-Version: 1.1
Name: JiveData
Version: 0.1
Summary: The code that powers www.jivedata.com, our email alerts, and twitter notifications
Home-page: https://www.jivedata.com
Author: Jive Data
Author-email: support@jivedata.com
License: BSD
Download-URL: https://github.com/jivedata/jivedata/tarball/0.1
Platform: any
Classifier: Development Status :: 5 - Production/Stable
Classifier: License :: OSI Approved :: BSD License
